{
  "$schema": "https://schema.management.azure.com/schemas/2015-01-01/deploymentTemplate.json#",
  "contentVersion": "1.0.0.0",
  "parameters": {
    "adminUsername": {
      "type": "string",
      "metadata": {
        "description": "The name of the administrator account of the new VM and domain"
      }
    },
    "adminPassword": {
      "type": "securestring",
      "metadata": {
        "description": "The password for the administrator account of the new VM and domain"
      }
    },
    "DCVMName": {
      "type": "string",
      "metadata": {
        "description": "The name of the DC to be created"
      }
    },
    "storageAccountName": {
      "type": "string",
      "metadata": {
        "description": "The name of the storage account for the DC"
      },
      "defaultValue": "igloostdstore"
    },
    "domainName": {
      "type": "string",
      "metadata": {
        "description": "The FQDN of the Active Directory Domain to be created"
      }
    },
    "adAvailabilitySetName": {
      "type": "string",
      "metadata": {
        "description": "The Availability set for the DCs"
      }
    },
    "virtualNetworkName": {
      "type": "string",
      "metadata": {
        "description": "The Availability set for the DCs"
      },
      "defaultValue": "Vnet-Igloo-POC"
    },
    "subnetName": {
      "type": "string",
      "metadata": {
        "description": "The Availability set for the DCs"
      },
      "defaultValue": "mgmt"
    },
    "_artifactsLocation": {
      "type": "string",
      "metadata": {
        "description": "The location of resources, such as templates and DSC modules, that the template depends on"
      },
      "defaultValue": "https://raw.githubusercontent.com/pierreroman/Igloo-POC/master/"
    },
    "_artifactsLocationSasToken": {
      "type": "securestring",
      "metadata": {
        "description": "Auto-generated token to access _artifactsLocation"
      },
      "defaultValue": ""
    }
  },
  "variables": {
    "adNicName": "adNic",
    "vnetId": "[resourceId(resourceGroup().name,'Microsoft.Network/virtualNetworks', parameters('virtualNetworkName'))]",
    "subnetRef": "[concat(variables('vnetId'), '/subnets/', parameters('subnetName'))]"
  },
  "resources": [
    {
      "type": "Microsoft.Storage/storageAccounts",
      "name": "[parameters('storageAccountName')]",
      "apiVersion": "2016-01-01",
      "location": "[resourceGroup().location]",
      "sku": {
        "name": "Standard_LRS"
      },
      "kind": "Storage",
      "properties": {}
    },
    {
      "type": "Microsoft.Network/networkInterfaces",
      "name": "[variables('adNicName')]",
      "apiVersion": "2016-03-30",
      "location": "[resourceGroup().location]",
      "dependsOn": [],
      "properties": {
        "ipConfigurations": [
          {
            "name": "ipconfig1",
            "properties": {
              "subnet": {
                "id": "[variables('subnetRef')]"
              },
              "privateIPAllocationMethod": "Dynamic"
            }
          }
        ]
      }
    },
    {
      "type": "Microsoft.Compute/virtualMachines",
      "name": "[parameters('DCVMName')]",
      "apiVersion": "2015-06-15",
      "location": "[resourceGroup().location]",
      "dependsOn": [
        "[resourceId('Microsoft.Network/networkInterfaces', variables('adNicName'))]",
        "[resourceId('Microsoft.Storage/storageAccounts', parameters('storageAccountName'))]"
      ],
      "properties": {
        "hardwareProfile": {
          "vmSize": "Standard_D2_v2"
        },
        "availabilitySet": {
          "id": "[resourceId('Microsoft.Compute/availabilitySets', parameters('adAvailabilitySetName'))]"
        },
        "osProfile": {
          "computerName": "[parameters('DCVMName')]",
          "adminUsername": "[parameters('adminUsername')]",
          "adminPassword": "[parameters('adminPassword')]"
        },
        "storageProfile": {
          "imageReference": {
            "publisher": "MicrosoftWindowsServer",
            "offer": "WindowsServer",
            "sku": "2012-R2-Datacenter",
            "version": "latest"
          },
          "osDisk": {
            "name": "osdisk",
            "vhd": {
              "uri": "[concat(reference(resourceId('Microsoft.Storage/storageAccounts', parameters('storageAccountName'))).primaryEndpoints.blob, 'vhds/', parameters('DCVMName'), '-os-disk.vhd')]"
            },
            "caching": "ReadWrite",
            "createOption": "FromImage"
          },
          "dataDisks": [
            {
              "vhd": {
                "uri": "[concat(reference(resourceId('Microsoft.Storage/storageAccounts', parameters('storageAccountName'))).primaryEndpoints.blob, 'vhds/', parameters('DCVMName'), '-data-disk.vhd')]"
              },
              "name": "[concat(parameters('DCVMName'), '-data-disk')]",
              "caching": "None",
              "createOption": "Empty",
              "diskSizeGB": "1000",
              "lun": 0
            }
          ]
        },
        "networkProfile": {
          "networkInterfaces": [
            {
              "id": "[resourceId('Microsoft.Network/networkInterfaces', variables('adNicName'))]"
            }
          ]
        }
      },
      "resources": [
        {
          "type": "extensions",
          "name": "CreateADForest",
          "apiVersion": "2015-06-15",
          "location": "[resourceGroup().location]",
          "dependsOn": [
            "[resourceId('Microsoft.Compute/virtualMachines', parameters('DCVMName'))]"
          ],
          "properties": {
            "publisher": "Microsoft.Powershell",
            "type": "DSC",
            "typeHandlerVersion": "2.19",
            "autoUpgradeMinorVersion": true,
            "settings": {
              "ModulesUrl": "[concat(parameters('_artifactsLocation'), '/DSC/CreateADPDC.zip', parameters('_artifactsLocationSasToken'))]",
              "ConfigurationFunction": "CreateADPDC.ps1\\CreateADPDC",
              "Properties": {
                "DomainName": "[parameters('domainName')]",
                "AdminCreds": {
                  "UserName": "[parameters('adminUsername')]",
                  "Password": "PrivateSettingsRef:AdminPassword"
                }
              }
            },
            "protectedSettings": {
              "Items": {
                "AdminPassword": "[parameters('adminPassword')]"
              }
            }
          }
        }
      ]
    }
  ]
}